je_auto_control/__init__.py
je_auto_control/__main__.py
je_auto_control/gui/__init__.py
je_auto_control/gui/main_widget.py
je_auto_control/gui/main_window.py
je_auto_control/gui/language_wrapper/__init__.py
je_auto_control/gui/language_wrapper/english.py
je_auto_control/gui/language_wrapper/multi_language_wrapper.py
je_auto_control/gui/language_wrapper/traditional_chinese.py
je_auto_control/linux_with_x11/__init__.py
je_auto_control/linux_with_x11/core/__init__.py
je_auto_control/linux_with_x11/core/utils/__init__.py
je_auto_control/linux_with_x11/core/utils/x11_linux_display.py
je_auto_control/linux_with_x11/core/utils/x11_linux_vk.py
je_auto_control/linux_with_x11/keyboard/__init__.py
je_auto_control/linux_with_x11/keyboard/x11_linux_keyboard_control.py
je_auto_control/linux_with_x11/listener/__init__.py
je_auto_control/linux_with_x11/listener/x11_linux_listener.py
je_auto_control/linux_with_x11/mouse/__init__.py
je_auto_control/linux_with_x11/mouse/x11_linux_mouse_control.py
je_auto_control/linux_with_x11/record/__init__.py
je_auto_control/linux_with_x11/record/x11_linux_record.py
je_auto_control/linux_with_x11/screen/__init__.py
je_auto_control/linux_with_x11/screen/x11_linux_screen.py
je_auto_control/osx/__init__.py
je_auto_control/osx/core/__init__.py
je_auto_control/osx/core/utils/__init__.py
je_auto_control/osx/core/utils/osx_vk.py
je_auto_control/osx/keyboard/__init__.py
je_auto_control/osx/keyboard/osx_keyboard.py
je_auto_control/osx/keyboard/osx_keyboard_check.py
je_auto_control/osx/listener/__init__.py
je_auto_control/osx/listener/osx_listener.py
je_auto_control/osx/mouse/__init__.py
je_auto_control/osx/mouse/osx_mouse.py
je_auto_control/osx/pid/__init__.py
je_auto_control/osx/pid/pid_control.py
je_auto_control/osx/record/__init__.py
je_auto_control/osx/record/osx_record.py
je_auto_control/osx/screen/__init__.py
je_auto_control/osx/screen/osx_screen.py
je_auto_control/utils/__init__.py
je_auto_control/utils/callback/__init__.py
je_auto_control_dev-0.0.132.dist-info/licenses/LICENSE
je_auto_control_dev-0.0.132.dist-info/METADATA
je_auto_control_dev-0.0.132.dist-info/WHEEL
je_auto_control_dev-0.0.132.dist-info/top_level.txt
je_auto_control_dev-0.0.132.dist-info/RECORD
